venumath/__init__.py
venumath/LcmGcd/GCD.py
venumath/LcmGcd/LCM.py
venumath/LcmGcd/__init__.py
venumath/advmath/__init__.py
venumath/advmath/expo.py
venumath/advmath/fibo.py
venumath/math/__init__.py
venumath/math/addition.py
venumath/math/division.py
venumath/math/mult.py
venumath/math/sub.py
venumath-1.0.0.dist-info/METADATA
venumath-1.0.0.dist-info/WHEEL
venumath-1.0.0.dist-info/top_level.txt
venumath-1.0.0.dist-info/RECORD
