Metadata-Version: 2.1
Name: venumath
Version: 1.0.0
Summary: My first Python package
Author: Venu K
Author-email: 2venukpython@gmail.com
Keywords: python,first package,Basic Mathamatic Operations
Classifier: Development Status :: 3 - Alpha
Classifier: Intended Audience :: Education
Classifier: Programming Language :: Python :: 2
Classifier: Programming Language :: Python :: 3
Classifier: Operating System :: MacOS :: MacOS X
Classifier: Operating System :: Microsoft :: Windows
